niadic_py/__init__.py
niadic_py/data/NIADic.csv
niadic_py/data/NIADic.xlsx
niadic_py/data/__init__.py
niadic_py/services/__init__.py
niadic_py/services/file_service.py
niadic_py/services/tokenizer_service.py
niadic_py/utils/__init__.py
niadic_py/utils/csv_utils.py
NIADic_py-0.0.1.dist-info/METADATA
NIADic_py-0.0.1.dist-info/WHEEL
NIADic_py-0.0.1.dist-info/top_level.txt
NIADic_py-0.0.1.dist-info/RECORD
