Metadata-Version: 2.1
Name: NIADic-py
Version: 0.0.1
Summary: Unofficial Python Wrapper for NIADic dataset
Author-email: minwook-shin <minwook0106@gmail.com>
Project-URL: Homepage, https://github.com/minwook-shin/niadic_py
Project-URL: Bug Tracker, https://github.com/minwook-shin/niadic_py/issues
Classifier: Programming Language :: Python :: 3
Classifier: License :: Other/Proprietary License
Classifier: Operating System :: OS Independent
Requires-Python: >=3.9
Requires-Dist: pandas ==2.1.1
Requires-Dist: openpyxl ==3.1.2
Requires-Dist: chardet ==5.2.0
Provides-Extra: dev
Requires-Dist: build ==1.0.3 ; extra == 'dev'
Requires-Dist: pdoc ==14.1.0 ; extra == 'dev'
